
<i>
<chatserver>chat.bilibili.com</chatserver>
<chatid>0</chatid>
<mission>0</mission>
<maxlimit>100000</maxlimit>
<source>k-v</source>

<d p="0.40329408645629883,1,25,16777215,0,0,0,0">笔记本6000+游戏本都差不多</d>
<d p="9.13211464881897,1,25,16777215,0,0,0,0">刺啦刺啦。。</d>
<d p="13.541644811630249,1,25,16777215,0,0,0,0">队友怎么不打</d>
<d p="13.642712354660034,1,25,16777215,0,0,0,0">麦克风</d>
<d p="15.046640396118164,1,25,16777215,0,0,0,0">R51400好还是i57500</d>
<d p="19.062976837158203,1,25,16777215,0,0,0,0">尬聊</d>
<d p="20.77276039123535,1,25,16777215,0,0,0,0">攻楼要用手雷不知道？</d>
<d p="24.990501165390015,1,25,16777215,0,0,0,0">狂鼠即将打不过天使</d>
<d p="25.994277477264404,1,25,16777215,0,0,0,0">哈哈。迈克，刺啦刺啦。</d>
<d p="29.008431434631348,1,25,16777215,0,0,0,0">53还是到东南亚服单排吧</d>
<d p="31.41481590270996,1,25,16777215,0,0,0,0">这游戏不吃cpu  吃内存和显卡 而已</d>
<d p="36.031005859375,1,25,16777215,0,0,0,0">主播会说英文的刺啦刺啦，关注了</d>
<d p="52.47837543487549,1,25,16777215,0,0,0,0">6G内存</d>
<d p="55.28858160972595,1,25,16777215,0,0,0,0">能玩吗</d>
<d p="57.094616174697876,1,25,16777215,0,0,0,0">你们用discord交流吗</d>
<d p="69.34016227722168,1,25,16777215,0,0,0,0">我8G都带不动啊</d>
<d p="70.1418285369873,1,25,16777215,0,0,0,0">1060  6G 显卡加8G内存 你玩不了算我输</d>
<d p="80.27480673789978,1,25,16777215,0,0,0,0">还准备再去加个内存条</d>
<d p="84.1839804649353,1,25,16777215,0,0,0,0">8g能玩，但这游戏要更新，最好配16g</d>
<d p="88.59562063217163,1,25,16777215,0,0,0,0">8g不太好的</d>
<d p="91.91329050064087,1,25,16777215,0,0,0,0">8g内存？最少12g</d>
<d p="95.62670373916626,1,25,16777215,0,0,0,0">你如果及时打死第一个人还有机会的</d>
<d p="98.13490033149719,1,25,16777215,0,0,0,0">你再吃不到鸡我就只能说你是娱乐主播了</d>
<d p="104.06743931770325,1,25,16777215,0,0,0,0">七夕还播吗</d>
<d p="106.87401914596558,1,25,16777215,0,0,0,0">事后诸葛亮</d>
<d p="111.38814282417297,1,25,16777215,0,0,0,0">金士顿 4G内存谁要啊？ 便宜卖</d>
<d p="114.9007294178009,1,25,16777215,0,0,0,0">七夕还播吗</d>
<d p="116.60502052307129,1,25,16777215,0,0,0,0">赶快吃鸡</d>
<d p="117.6079671382904,1,25,16777215,0,0,0,0">内存Kst8g2400   显卡1050，怎么样</d>
<d p="123.72708368301392,1,25,16777215,0,0,0,0">雾山    守望下个版本你将会经常被天使单杀</d>
<d p="126.23019051551819,1,25,16777215,0,0,0,0">没战术意识</d>
<d p="127.23236036300659,1,25,16777215,0,0,0,0">妹纸主播</d>
<d p="129.73822689056396,1,25,16777215,0,0,0,0">53还是到东南亚服单排吧，</d>
<d p="133.6712131500244,1,25,16777215,0,0,0,0">53英语这么好？  惊了</d>
<d p="135.98053169250488,1,25,16777215,0,0,0,0">多少啊内存条，90收</d>
<d p="136.583984375,1,25,16777215,0,0,0,0">来个人带带53吧</d>
<d p="140.99695777893066,1,25,16777215,0,0,0,0">天使咋了。</d>
<d p="142.00115942955017,1,25,16777215,0,0,0,0">我来帮群友问问，外国小哥用的什么加速器</d>
<d p="143.3054850101471,1,25,16777215,0,0,0,0">这小哥麦有时候有点问题 听不太清</d>
<d p="150.22629570960999,1,25,16777215,0,0,0,0">天使什么情况</d>
<d p="152.2320487499237,1,25,16777215,0,0,0,0">再厉害也只是个奶</d>
<d p="152.53294372558594,1,25,16777215,0,0,0,0">战斗天使 </d>
<d p="153.73535680770874,1,25,16777215,0,0,0,0">天使有复活甲</d>
<d p="156.4421730041504,1,25,16777215,0,0,0,0">我买个4600的笔记本用了一年就不想用了</d>
<d p="159.85462307929993,1,25,16777215,0,0,0,0">53应该快30岁了吧，看着挺成熟的</d>
<d p="160.15567684173584,1,25,16777215,0,0,0,0">很厉害，刚刚看完开发者访谈</d>
<d p="166.67494320869446,1,25,16777215,0,0,0,0">想看单排啊53</d>
<d p="179.6376576423645,1,25,16777215,0,0,0,0">昨天抢刚</d>
<d p="181.0430405139923,1,25,16777215,0,0,0,0">打身上40    包头80     子弹无限    自己可以飞  </d>
<d p="181.14399433135986,1,25,16777215,0,0,0,0">53</d>
<d p="184.65304565429688,1,25,16777215,0,0,0,0">问问小哥用的什么加速器</d>
<d p="196.89050674438477,1,25,16777215,0,0,0,0">到现在吃了一次鸡吗</d>
<d p="202.71220231056213,1,25,16777215,0,0,0,0">雾山</d>
<d p="234.40403604507446,1,25,16777215,0,0,0,0">这样直播效果并不好</d>
<d p="236.91036939620972,1,25,16777215,0,0,0,0">雾山口语好棒啊</d>
<d p="251.16091680526733,1,25,16777215,0,0,0,0">这样挺欢乐的  挺好</d>
<d p="260.49173164367676,1,25,16777215,0,0,0,0">金士顿4G内存条  谁要啊 便宜卖</d>
<d p="262.0981366634369,1,25,16777215,0,0,0,0">这小哥人很好，可以叫来线下玩</d>
<d p="270.92636466026306,1,25,16777215,0,0,0,0">我是来学外语的</d>
<d p="274.8356411457062,1,25,16777215,0,0,0,0">4g内存条多少钱啊</d>
<d p="293.19051480293274,1,25,16777215,0,0,0,0">200有找</d>
<d p="294.2979233264923,1,25,16777215,0,0,0,0">这好多抢啊</d>
<d p="294.6991913318634,1,25,16777215,0,0,0,0">加我QQ 549544314</d>
<d p="307.13482117652893,1,25,16777215,0,0,0,0">我是来看吃鸡的，</d>
<d p="315.9594328403473,1,25,16777215,0,0,0,0">把枪子弹全捡了别留给别人</d>
<d p="338.3384470939636,1,25,16777215,0,0,0,0">弹幕还能卖内存条233</d>
<d p="340.04343914985657,1,25,16777215,0,0,0,0">4600的华硕用了一年可以卖多少钱</d>
<d p="350.27522325515747,1,25,16777215,0,0,0,0">2300</d>
<d p="351.0783498287201,1,25,16777215,0,0,0,0">4513</d>
<d p="372.84198117256165,1,25,16777215,0,0,0,0">还是那个美国男朋友？</d>
<d p="388.6957242488861,1,25,16777215,0,0,0,0">一般去哪里卖</d>
<d p="388.69622468948364,1,25,16777215,0,0,0,0">头不要？</d>
<d p="391.50571846961975,1,25,16777215,0,0,0,0">又换了个~</d>
<d p="392.5103199481964,1,25,16777215,0,0,0,0">1050显卡怎么样  ？</d>
<d p="404.7507336139679,1,25,16777215,0,0,0,0">急救包给她</d>
<d p="406.0541362762451,1,25,16777215,0,0,0,0">1050不怎么样的 买1060吧</d>
<d p="412.0007269382477,1,25,16777215,0,0,0,0">给他药</d>
<d p="415.3135347366333,1,25,16777215,0,0,0,0">我要看53帅气的脸可以么</d>
<d p="417.72107911109924,1,25,16777215,0,0,0,0">换队友了嘛？</d>
<d p="418.8265600204468,1,25,16777215,0,0,0,0">1050没问题</d>
<d p="430.1601734161377,1,25,16777215,0,0,0,0">1050俗称智商检测卡</d>
<d p="430.4624128341675,1,25,16777215,0,0,0,0">雾山色相头呢</d>
<d p="435.0726041793823,1,25,16777215,0,0,0,0">8g内存够吗？</d>
<d p="439.5838599205017,1,25,16777215,0,0,0,0">扼流圈可以要的啊</d>
<d p="441.9909842014313,1,25,16777215,0,0,0,0">咬咬牙加点钱上1070</d>
<d p="443.69544887542725,1,25,16777215,0,0,0,0">头</d>
<d p="445.5030553340912,1,25,16777215,0,0,0,0">8G内存玩两把就卡了</d>
<d p="453.2287666797638,1,25,16777215,0,0,0,0">没拿头</d>
<d p="454.4310414791107,1,25,16777215,0,0,0,0">智商检测卡的，你把1030放哪？</d>
<d p="454.6327819824219,1,25,16777215,0,0,0,0">8G加个4G的条子变成12G吧，</d>
<d p="454.9340913295746,1,25,16777215,0,0,0,0">32g内存够用</d>
<d p="469.87768054008484,1,25,16777215,0,0,0,0">我有个闲置的4G内存条  谁要啊</d>
<d p="475.2982361316681,1,25,16777215,0,0,0,0">内存条不贵的</d>
<d p="487.6369831562042,1,25,16777215,0,0,0,0">53不玩守望了吗</d>
<d p="488.74067544937134,1,25,16777215,0,0,0,0">不是三级头不捡</d>
<d p="493.35495829582214,1,25,16777215,0,0,0,0">d3 1600 4g 200多一点</d>
<d p="496.8621165752411,1,25,16777215,0,0,0,0">50包邮</d>
<d p="505.68611001968384,1,25,16777215,0,0,0,0">现在一个8G的也要不了几个钱啊</d>
<d p="518.3318424224854,1,25,16777215,0,0,0,0">8G金士顿1600 300多</d>
<d p="521.1376118659973,1,25,16777215,0,0,0,0">你的头上绿的发亮</d>
<d p="524.9532561302185,1,25,16777215,0,0,0,0">1600的太次了。</d>
<d p="527.9624502658844,1,25,16777215,0,0,0,0">带波节奏：大神gtx960       8g能玩吗</d>
<d p="529.1654036045074,1,25,16777215,0,0,0,0">买双通道呗，</d>
<d p="530.5711989402771,1,25,16777215,0,0,0,0">90块卖不</d>
<d p="530.7718205451965,1,25,16777215,0,0,0,0">现在网上内存条便宜</d>
<d p="531.6746406555176,1,25,16777215,0,0,0,0">雾山带老美吃了几只鸡</d>
<d p="538.3044264316559,1,25,16777215,0,0,0,0">你头上有呼伦贝尔</d>
<d p="549.7418801784515,1,25,16777215,0,0,0,0">d4，8g现在四百多五百一条，这叫不贵？</d>
<d p="551.046995639801,1,25,16777215,0,0,0,0">普通人，玩游戏，内存频率跟你没什么关系</d>
<d p="573.4210085868835,1,25,16777215,0,0,0,0">没钱先把cpu和内存弄好 这游戏不吃显卡</d>
<d p="576.9332051277161,1,25,16777215,0,0,0,0">倍镜怎么说？。。。。</d>
<d p="577.1344680786133,1,25,16777215,0,0,0,0">这个游戏内存频率还是有点关系的</d>
<d p="579.5428130626678,1,25,16777215,0,0,0,0">我在京东上直接买一体机，能玩这个游戏的，有推荐的么</d>
<d p="580.2450473308563,1,25,16777215,0,0,0,0">美国小哥电音高手</d>
<d p="583.0568771362305,1,25,16777215,0,0,0,0">你们用的是什么语音</d>
<d p="584.4626071453094,1,25,16777215,0,0,0,0">还要加速器</d>
<d p="585.063747882843,1,25,16777215,0,0,0,0">内存条比以前便宜太多了</d>
<d p="593.5149178504944,1,25,16777215,0,0,0,0">天降正义</d>
<d p="596.8277626037598,1,25,16777215,0,0,0,0">那就买D3 1866</d>
<d p="602.4464800357819,1,25,16777215,0,0,0,0">以前便宜老哥</d>
<d p="603.6510307788849,1,25,16777215,0,0,0,0">瞎搞 先把内存个显卡弄好</d>
<d p="606.1576242446899,1,25,16777215,0,0,0,0">有国度了应该能不用加速器了</d>
<d p="609.4788658618927,1,25,16777215,0,0,0,0">CPU差不多就行</d>
<d p="610.2822391986847,1,25,16777215,0,0,0,0">真没必要买高频内存</d>
<d p="612.0894949436188,1,25,16777215,0,0,0,0">国服</d>
<d p="617.4086105823517,1,25,16777215,0,0,0,0">三星出事那段时间 内存条平均涨了50多</d>
<d p="625.0251796245575,1,25,16777215,0,0,0,0">除非你是八核，十核</d>
<d p="629.6399681568146,1,25,16777215,0,0,0,0">加个内存条就行了</d>
<d p="629.7407119274139,1,25,16777215,0,0,0,0">4G金士顿 内存条  要的加我QQ 549544314</d>
<d p="632.6500401496887,1,25,16777215,0,0,0,0">今年下半年内存贼贵好么，翻一番了快</d>
<d p="633.3530666828156,1,25,16777215,0,0,0,0">最近挖矿火 显卡又他妈贵了</d>
<d p="648.3016033172607,1,25,16777215,0,0,0,0">游戏不太吃显卡cpu,主要吃内存</d>
<d p="660.3453381061554,1,25,16777215,0,0,0,0">吃主板</d>
<d p="663.9550211429596,1,25,16777215,0,0,0,0">没钱也要把显卡弄好的我也是醉了</d>
<d p="665.9616918563843,1,25,16777215,0,0,0,0">不吃显卡?</d>
<d p="670.6780006885529,1,25,16777215,0,0,0,0">吃鸡</d>
<d p="677.6010203361511,1,25,16777215,0,0,0,0">吃鸭</d>
<d p="678.8035469055176,1,25,16777215,0,0,0,0">这游戏吃电源</d>
<d p="680.2092707157135,1,25,16777215,0,0,0,0">8g内存条处理 要的加我QQ545688712</d>
<d p="680.5107760429382,1,25,16777215,0,0,0,0">这游戏什么都吃，连小孩都吃</d>
<d p="681.1190519332886,1,25,16777215,0,0,0,0">吃电源</d>
<d p="687.8423075675964,1,25,16777215,0,0,0,0">这哟样子</d>
<d p="690.3736860752106,1,25,16777215,0,0,0,0">内存价格和cpu显卡比起来真的不算什么</d>
<d p="691.175763130188,1,25,16777215,0,0,0,0">装个配电箱就不卡了</d>
<d p="691.2768647670746,1,25,16777215,0,0,0,0">这游戏吃内存和显存</d>
<d p="695.0068166255951,1,25,16777215,0,0,0,0">这游戏</d>
<d p="699.820175409317,1,25,16777215,0,0,0,0">吃钱</d>
<d p="704.3365137577057,1,25,16777215,0,0,0,0">没钱去网吧玩，网吧玩还有感觉些</d>
<d p="704.9395580291748,1,25,16777215,0,0,0,0">显卡1050都可以</d>
<d p="707.0447890758514,1,25,16777215,0,0,0,0">这游戏吃鸡 吃啥自行车</d>
<d p="709.4519507884979,1,25,16777215,0,0,0,0">吃智商</d>
<d p="713.0622828006744,1,25,16777215,0,0,0,0">我730都照完。。</d>
<d p="714.968808889389,1,25,16777215,0,0,0,0">16x2的内存都2000多辣</d>
<d p="715.4710762500763,1,25,16777215,0,0,0,0">这游戏没有1070别玩</d>
<d p="715.9741628170013,1,25,16777215,0,0,0,0">这游戏A黑，最好是十系N卡</d>
<d p="719.3840508460999,1,25,16777215,0,0,0,0">这把吃鸡，硫酸擦鸡！大家知道我是谁了把！</d>
<d p="721.9996418952942,1,25,16777215,0,0,0,0">cpu是越高越好吗</d>
<d p="727.3257367610931,1,25,16777215,0,0,0,0">照你这么说电脑价格真不算什么</d>
<d p="733.9534318447113,1,25,16777215,0,0,0,0">明明是吃鼠标 ，各位大佬都别唧唧了</d>
<d p="740.8768320083618,1,25,16777215,0,0,0,0">一般网吧30帧</d>
<d p="749.7019658088684,1,25,16777215,0,0,0,0">吃屌</d>
<d p="754.7172727584839,1,25,16777215,0,0,0,0">低配 730显卡 12G内存 跑起来66的 不卡</d>
<d p="767.8548181056976,1,25,16777215,0,0,0,0">730是在说笑</d>
<d p="775.1728458404541,1,25,16777215,0,0,0,0">网吧得好点的，电竞专区，比一般的贵</d>
<d p="778.7825922966003,1,25,16777215,0,0,0,0">别说了这游戏吃鸡</d>
<d p="784.6006939411163,1,25,16777215,0,0,0,0">cpu g4560以上就可以</d>
<d p="786.4047956466675,1,25,16777215,0,0,0,0">你不信我能说什么</d>
<d p="801.0489604473114,1,25,16777215,0,0,0,0">1070  66666  没1080ti你能玩游戏？</d>
<d p="808.2678401470184,1,25,16777215,0,0,0,0">去网咖玩配置就够，普通网吧带着卡</d>
<d p="809.6725518703461,1,25,16777215,0,0,0,0">你懂不卡的意思是什么吗</d>
<d p="821.2117419242859,1,25,16777215,0,0,0,0">这游戏画质一般般，这么吃硬件</d>
<d p="824.6180210113525,1,25,16777215,0,0,0,0">走那边</d>
<d p="827.2267782688141,1,25,16777215,0,0,0,0">还跟这货双排啊</d>
<d p="834.0483026504517,1,25,16777215,0,0,0,0">那边</d>
<d p="836.6573822498322,1,25,16777215,0,0,0,0">箱子上</d>
<d p="836.6593837738037,1,25,16777215,0,0,0,0">箱子啊</d>
<d p="838.5671453475952,1,25,16777215,0,0,0,0">这游戏玩好玩爽要中高60帧吧？</d>
<d p="840.9744329452515,1,25,16777215,0,0,0,0">各位大神 1230V3能玩不</d>
<d p="841.4755365848541,1,25,16777215,0,0,0,0">上面高的</d>
<d p="842.7794382572174,1,25,16777215,0,0,0,0">开车搭下下边</d>
<d p="843.0807282924652,1,25,16777215,0,0,0,0">右边</d>
<d p="844.4833636283875,1,25,16777215,0,0,0,0">枪换下了</d>
<d p="847.0906803607941,1,25,16777215,0,0,0,0">武器收起来</d>
<d p="847.4919955730438,1,25,16777215,0,0,0,0">想要玩得6起来最低1070</d>
<d p="849.797135591507,1,25,16777215,0,0,0,0">双手</d>
<d p="850.499263048172,1,25,16777215,0,0,0,0">加速跑</d>
<d p="850.7008371353149,1,25,16777215,0,0,0,0">算了吧</d>
<d p="856.9208719730377,1,25,16777215,0,0,0,0">超级跳</d>
<d p="858.6507818698883,1,25,16777215,0,0,0,0">能跳一天</d>
<d p="860.2554755210876,1,25,16777215,0,0,0,0">先跳桶上</d>
<d p="860.757310628891,1,25,16777215,0,0,0,0">这游戏不是正式版，而且是虚幻4</d>
<d p="864.289071559906,1,25,16777215,0,0,0,0">双手</d>
<d p="865.9270441532135,1,25,16777215,0,0,0,0">前面的箱子</d>
<d p="866.1280832290649,1,25,16777215,0,0,0,0">人梯</d>
<d p="866.8307459354401,1,25,16777215,0,0,0,0">1060够了</d>
<d p="867.7318956851959,1,25,16777215,0,0,0,0">ptr看了吗53</d>
<d p="868.6350040435791,1,25,16777215,0,0,0,0">武器</d>
<d p="873.9706892967224,1,25,16777215,0,0,0,0">换一个方向啊</d>
<d p="877.9862332344055,1,25,16777215,0,0,0,0">1050可以了</d>
<d p="877.9872357845306,1,25,16777215,0,0,0,0">源二段跳能过</d>
<d p="897.5476818084717,1,25,16777215,0,0,0,0">玩的好不好是靠技术不是靠你买个显卡</d>
<d p="898.8515825271606,1,25,16777215,0,0,0,0">画质是真心一般般</d>
<d p="904.1637165546417,1,25,16777215,0,0,0,0">吧武器花哪了</d>
<d p="908.2759754657745,1,25,16777215,0,0,0,0">吧武器换了</d>
<d p="913.9087159633636,1,25,16777215,0,0,0,0">狂鼠shift过去</d>
<d p="918.317391872406,1,25,16777215,0,0,0,0">30帧不到你吃鸡我看看</d>
<d p="944.2013871669769,1,25,16777215,0,0,0,0">某些大神就是买显卡买显示器 最后还是个傻吊</d>
<d p="963.0617246627808,1,25,16777215,0,0,0,0">哈哈哈哈</d>
<d p="973.1880097389221,1,25,16777215,0,0,0,0">那些有钱人爱买144hz你管他</d>
<d p="974.7950809001923,1,25,16777215,0,0,0,0">你这逻辑有问题啊</d>
<d p="1008.3229625225067,1,25,16777215,0,0,0,0">53的枪真的刚</d>
<d p="1008.6250109672546,1,25,16777215,0,0,0,0">别的主播都是这个妹子那个妹子。</d>
<d p="1019.2759716510773,1,25,16777215,0,0,0,0">53你是这个小哥那个小哥</d>
<d p="1024.5000126361847,1,25,16777215,0,0,0,0">反正我玩的不好原因很多 反正不是我</d>
<d p="1026.6049835681915,1,25,16777215,0,0,0,0">哈哈哈哈</d>
<d p="1029.0202145576477,1,25,16777215,0,0,0,0">66666666666</d>
<d p="1038.6675477027893,1,25,16777215,0,0,0,0">小哥，小妹</d>
<d p="1053.5167906284332,1,25,16777215,0,0,0,0">我发现 看弹幕 总是比看直播有乐趣</d>
<d p="1062.337602853775,1,25,16777215,0,0,0,0">平底锅</d>
<d p="1062.8393833637238,1,25,16777215,0,0,0,0">国际友人</d>
<d p="1070.6723895072937,1,25,16777215,0,0,0,0">锅</d>
<d p="1075.8850605487823,1,25,16777215,0,0,0,0">平底锅啊</d>
<d p="1076.086025238037,1,25,16777215,0,0,0,0">53什么时候带妹子吃鸡</d>
<d p="1076.9878227710724,1,25,16777215,0,0,0,0">锅</d>
<d p="1077.5887444019318,1,25,16777215,0,0,0,0">有锅</d>
<d p="1077.9905128479004,1,25,16777215,0,0,0,0">锅</d>
<d p="1077.991013288498,1,25,16777215,0,0,0,0">锅</d>
<d p="1078.8934888839722,1,25,16777215,0,0,0,0">求国际QQ，</d>
<d p="1079.9965858459473,1,25,16777215,0,0,0,0">平底锅什么用呀</d>
<d p="1080.0981500148773,1,25,16777215,0,0,0,0">挡子弹的</d>
<d p="1081.403172492981,1,25,16777215,0,0,0,0">锅呀</d>
<d p="1083.1109817028046,1,25,16777215,0,0,0,0">平底锅</d>
<d p="1083.6134688854218,1,25,16777215,0,0,0,0">听得懂？</d>
<d p="1083.8146386146545,1,25,16777215,0,0,0,0"> 锅没拿</d>
<d p="1085.8242228031158,1,25,16777215,0,0,0,0">锅没拿</d>
<d p="1085.8252234458923,1,25,16777215,0,0,0,0">神锅</d>
<d p="1088.8346905708313,1,25,16777215,0,0,0,0">锅</d>
<d p="1089.3370888233185,1,25,16777215,0,0,0,0">护肛神器</d>
<d p="1089.738478899002,1,25,16777215,0,0,0,0">锅没拿</d>
<d p="1093.7513072490692,1,25,16777215,0,0,0,0">平底锅神器</d>
<d p="1096.257513999939,1,25,16777215,0,0,0,0">锅挡屁股啊</d>
<d p="1111.305067539215,1,25,16777215,0,0,0,0">护菊利器</d>
<d p="1113.8153564929962,1,25,16777215,0,0,0,0">锅没拿！！！</d>
<d p="1117.6319432258606,1,25,16777215,0,0,0,0">这里死哥箱子</d>
<d p="1125.5603306293488,1,25,16777215,0,0,0,0">锅</d>
<d p="1126.5650398731232,1,25,16777215,0,0,0,0">四级甲</d>
<d p="1129.2712123394012,1,25,16777215,0,0,0,0">身上有锅</d>
<d p="1131.778858423233,1,25,16777215,0,0,0,0">不带妹纸没排面</d>
<d p="1140.6062183380127,1,25,16777215,0,0,0,0">有</d>
<d p="1143.8174049854279,1,25,16777215,0,0,0,0">医疗兵53向你报告</d>
<d p="1151.5438034534454,1,25,16777215,0,0,0,0">声音</d>
<d p="1153.6514089107513,1,25,16777215,0,0,0,0">反正相信我想吃鸡就得7000以上电脑</d>
<d p="1153.7520773410797,1,25,16777215,0,0,0,0">有，要烂了</d>
<d p="1160.4725630283356,1,25,16777215,0,0,0,0">有个坏的二级头</d>
<d p="1161.174750328064,1,25,16777215,0,0,0,0">66666666666</d>
<d p="1161.77800989151,1,25,16777215,0,0,0,0">有个二级一丝血</d>
<d p="1167.2977998256683,1,25,16777215,0,0,0,0">快烂了</d>
<d p="1168.5028183460236,1,25,16777215,0,0,0,0">半血二级头</d>
<d p="1170.612572669983,1,25,16777215,0,0,0,0">有个二级但是坏了</d>
<d p="1186.1034910678864,1,25,16777215,0,0,0,0">坏的高等级头盔也比漫的低等级好用</d>
<d p="1194.129029750824,1,25,16777215,0,0,0,0">总比一级的好吧</d>
<d p="1199.945816040039,1,25,16777215,0,0,0,0">53人气多少了？上万吗</d>
<d p="1226.9281947612762,1,25,16777215,0,0,0,0">53上首页了</d>
<d p="1229.0328524112701,1,25,16777215,0,0,0,0">一起血的三级头盔也能防被98k爆头</d>
<d p="1233.7705914974213,1,25,16777215,0,0,0,0">码率真的是低</d>
<d p="1236.1808853149414,1,25,16777215,0,0,0,0">为啥我这里了显示5000多</d>
<d p="1264.3603773117065,1,25,16777215,0,0,0,0">可以的，qq叔帮了好些主播涨人气。</d>
<d p="1270.3786714076996,1,25,16777215,0,0,0,0">98K打3级偷 满血死不掉</d>
<d p="1272.3857367038727,1,25,16777215,0,0,0,0">我刚刚去打了一美服 感觉好简答</d>
<d p="1274.4912431240082,1,25,16777215,0,0,0,0">气氛尴尬</d>
<d p="1277.9057116508484,1,25,16777215,0,0,0,0">两个原谅帽</d>
<d p="1279.1130883693695,1,25,16777215,0,0,0,0">亚服简直是地狱</d>
<d p="1283.1209971904755,1,25,16777215,0,0,0,0">服务器炸了？</d>
<d p="1283.623507976532,1,25,16777215,0,0,0,0">53枪是刚</d>
<d p="1291.253722667694,1,25,16777215,0,0,0,0">亚服人太多了</d>
<d p="1291.455575466156,1,25,16777215,0,0,0,0">又是厕所。</d>
<d p="1293.4641993045807,1,25,16777215,0,0,0,0">服务器炸了</d>
<d p="1301.3832552433014,1,25,16777215,0,0,0,0">教外国佬蹲厕所</d>
<d p="1306.7986221313477,1,25,16777215,0,0,0,0">熟悉的地方</d>
<d p="1310.0109915733337,1,25,16777215,0,0,0,0">53英语这么6了啊</d>
<d p="1321.350094795227,1,25,16777215,0,0,0,0">你闷2个人躲着 别人把你们的车开了咋弄</d>
<d p="1325.8633031845093,1,25,16777215,0,0,0,0">熟悉的地方熟悉的味道</d>
<d p="1349.7308793067932,1,25,16777215,0,0,0,0">进不去了？</d>
<d p="1359.1631190776825,1,25,16777215,0,0,0,0">越南小哥战斗过的地方</d>
<d p="1367.5914900302887,1,25,16777215,0,0,0,0">服务器关了？</d>
<d p="1371.704526424408,1,25,16777215,0,0,0,0">我感觉雾山好像某公司的高级管理，因为游戏不做了</d>
<d p="1395.911463022232,1,25,16777215,0,0,0,0">想多了</d>
<d p="1405.2366383075714,1,25,16777215,0,0,0,0">老外得语音断断续续的啊</d>
<d p="1408.9508030414581,1,25,16777215,0,0,0,0">其实53放弃了上千亿家产继承，就是为了电竞梦</d>
<d p="1411.1640050411224,1,25,16777215,0,0,0,0">wow</d>
<d p="1416.3994336128235,1,25,16777215,0,0,0,0">被小姨子拐跑了吗</d>
<d p="1425.039866924286,1,25,16777215,0,0,0,0">这几天h1z1禁播，53要抓紧吸引h1z1转吃鸡的观众</d>
<d p="1426.4605679512024,1,25,16777215,0,0,0,0">并不冲突吧- -！、</d>
<d p="1426.86834025383,1,25,16777215,0,0,0,0">WOW your english is very good</d>
<d p="1429.273014307022,1,25,16777215,0,0,0,0">看气质就是有一定社会地位的人士</d>
<d p="1434.3906466960907,1,25,16777215,0,0,0,0">雾山还是帅的</d>
<d p="1452.5546510219574,1,25,16777215,0,0,0,0">这么远。</d>
<d p="1455.0642347335815,1,25,16777215,0,0,0,0">要调归零点到200打的到</d>
<d p="1469.9101428985596,1,25,16777215,0,0,0,0">啪啪啪打脸</d>
<d p="1476.133038520813,1,25,16777215,0,0,0,0">百步穿杨</d>
<d p="1481.75151181221,1,25,16777215,0,0,0,0">666666</d>
<d p="1481.952145576477,1,25,16777215,0,0,0,0">消音器还是屌啊</d>
<d p="1482.9554226398468,1,25,16777215,0,0,0,0">打久了 就知道怎么打了</d>
<d p="1483.957977771759,1,25,16777215,0,0,0,0">去舔</d>
<d p="1495.1093180179596,1,25,16777215,0,0,0,0">我人都没见到，就打死一个</d>
<d p="1495.6110475063324,1,25,16777215,0,0,0,0">dead</d>
<d p="1503.7363579273224,1,25,16777215,0,0,0,0">舔包</d>
<d p="1506.347204208374,1,25,16777215,0,0,0,0">这时候去舔找死么……</d>
<d p="1521.198534488678,1,25,16777215,0,0,0,0">舔她啊，老哥</d>
<d p="1531.0322976112366,1,25,16777215,0,0,0,0">队友不是98k吗</d>
<d p="1537.1494722366333,1,25,16777215,0,0,0,0">厉害了我的53</d>
<d p="1544.679930448532,1,25,16777215,0,0,0,0">服务器炸了吧？</d>
<d p="1554.8152360916138,1,25,16777215,0,0,0,0">服务器炸了</d>
<d p="1555.1160621643066,1,25,16777215,0,0,0,0">5000里开外打死鬼子</d>
<d p="1557.4257514476776,1,25,16777215,0,0,0,0">这事游戏里语音吗？</d>
<d p="1572.9738030433655,1,25,16777215,0,0,0,0">服务进不去</d>
<d p="1582.0099296569824,1,25,16777215,0,0,0,0">53现在不看弹幕吗？</d>
<d p="1584.3194658756256,1,25,16777215,0,0,0,0">你们说的什么服务器啊</d>
<d p="1585.8244059085846,1,25,16777215,0,0,0,0">电磁脉冲来了估计要gg</d>
<d p="1587.9306304454803,1,25,16777215,0,0,0,0">反正中国制英语能听懂。美国听不懂</d>
<d p="1598.65789103508,1,25,16777215,0,0,0,0">                 </d>
<d p="1600.6652572154999,1,25,16777215,0,0,0,0">打胎吗</d>
<d p="1618.2224400043488,1,25,16777215,0,0,0,0">天命</d>
<d p="1622.8394706249237,1,25,16777215,0,0,0,0"> </d>
<d p="1623.4415440559387,1,25,16777215,0,0,0,0">天命圈</d>
<d p="1630.2672889232635,1,25,16777215,0,0,0,0">   </d>
<d p="1633.9834280014038,1,25,16777215,0,0,0,0">这是要？</d>
<d p="1642.8089706897736,1,25,16777215,0,0,0,0">又是这条河</d>
<d p="1650.9268641471863,1,25,16777215,0,0,0,0">    </d>
<d p="1656.2423508167267,1,25,16777215,0,0,0,0">又要靠手雷杀人了</d>
<d p="1657.1445167064667,1,25,16777215,0,0,0,0">下去啊</d>
<d p="1678.715129852295,1,25,16777215,0,0,0,0">现在下去容易死吧</d>
<d p="1680.5239593982697,1,25,16777215,0,0,0,0">周围都是人，下去送？</d>
<d p="1687.8481814861298,1,25,16777215,0,0,0,0">2个人还有一个 走了 杀了他</d>
<d p="1691.8640053272247,1,25,16777215,0,0,0,0">去玩了一下手游，回来怎么你两不逗比了？好认真的感觉</d>
<d p="1708.1129868030548,1,25,16777215,0,0,0,0">有回音啊</d>
<d p="1722.1539347171783,1,25,16777215,0,0,0,0">跑一波毒呀</d>
<d p="1725.466076850891,1,25,16777215,0,0,0,0">美国现在是后半夜吧= =</d>
<d p="1729.177885055542,1,25,16777215,0,0,0,0">服务器炸了吗</d>
<d p="1731.3863973617554,1,25,16777215,0,0,0,0">熬夜打游戏</d>
<d p="1742.1244323253632,1,25,16777215,0,0,0,0">小哥天天修仙</d>
<d p="1762.7827014923096,1,25,16777215,0,0,0,0">现在美国什么时候？</d>
<d p="1763.0842998027802,1,25,16777215,0,0,0,0">河对岸？</d>
<d p="1768.3974702358246,1,25,16777215,0,0,0,0">后半夜了</d>
<d p="1785.9558572769165,1,25,16777215,0,0,0,0">看美国什么洲</d>
<d p="1795.7966783046722,1,25,16777215,0,0,0,0">当水鬼</d>
<d p="1798.3043451309204,1,25,16777215,0,0,0,0">老美尼玛炸了you no</d>
<d p="1804.0242218971252,1,25,16777215,0,0,0,0">.</d>
<d p="1809.743821144104,1,25,16777215,0,0,0,0">哈哈哈</d>
<d p="1817.3750517368317,1,25,16777215,0,0,0,0">哎呀 好气啊</d>
<d p="1823.8135385513306,1,25,16777215,0,0,0,0">这个英语666</d>
<d p="1826.1255097389221,1,25,16777215,0,0,0,0">老美麦不行啊</d>
<d p="1832.6489007472992,1,25,16777215,0,0,0,0">here here。。</d>
<d p="1839.7722465991974,1,25,16777215,0,0,0,0">这是网不行，不是麦</d>
<d p="1843.486002445221,1,25,16777215,0,0,0,0">是网络问题 不是麦克</d>
<d p="1847.8014285564423,1,25,16777215,0,0,0,0">队友可以</d>
<d p="1853.8200662136078,1,25,16777215,0,0,0,0">开个vpn啊</d>
<d p="1854.3229429721832,1,25,16777215,0,0,0,0">这枪可以 </d>
<d p="1856.729928970337,1,25,16777215,0,0,0,0">这 小哥哥可以的啊</d>
<d p="1856.9315629005432,1,25,16777215,0,0,0,0">这集我昨天看过了，吃鸡了</d>
<d p="1857.232764005661,1,25,16777215,0,0,0,0">服务器怎么了</d>
<d p="1858.3362531661987,1,25,16777215,0,0,0,0">老美的ju好准</d>
<d p="1866.1640267372131,1,25,16777215,0,0,0,0">给小哥要啊</d>
<d p="1870.579404592514,1,25,16777215,0,0,0,0">美国小哥6啊</d>
<d p="1875.0963792800903,1,25,16777215,0,0,0,0">换头啊</d>
<d p="1879.008538722992,1,25,16777215,0,0,0,0">换头盔啊</d>
<d p="1881.0157353878021,1,25,16777215,0,0,0,0">小哥没药</d>
<d p="1883.32408618927,1,25,16777215,0,0,0,0">这边开始connectionclosed</d>
<d p="1899.7811193466187,1,25,16777215,0,0,0,0">吃鸡维护了？我咋进不去</d>
<d p="1901.990049123764,1,25,16777215,0,0,0,0">6666666666666666</d>
<d p="1904.4997282028198,1,25,16777215,0,0,0,0">ggg</d>
<d p="1917.9556403160095,1,25,16777215,0,0,0,0">吃鸡</d>
<d p="1918.6595225334167,1,25,16777215,0,0,0,0">吃鸡了</d>
<d p="1920.9703698158264,1,25,16777215,0,0,0,0">吃鸡了</d>
<d p="1927.6904549598694,1,25,16777215,0,0,0,0">吃鸡</d>
<d p="1930.2018291950226,1,25,16777215,0,0,0,0">还没到最后呢</d>
<d p="1935.6431877613068,1,25,16777215,0,0,0,0">这把一定吃鸡</d>
<d p="1938.1529529094696,1,25,16777215,0,0,0,0">哈哈哈哈</d>
<d p="1941.2648057937622,1,25,16777215,0,0,0,0">AWM？</d>
<d p="1944.5775542259216,1,25,16777215,0,0,0,0">m24</d>
<d p="1945.3814041614532,1,25,16777215,0,0,0,0">几何鼠？</d>
<d p="1950.6094253063202,1,25,16777215,0,0,0,0">打地鼠</d>
<d p="1963.745332956314,1,25,16777215,0,0,0,0">这是M24的声音？</d>
<d p="1977.4927818775177,1,25,16777215,0,0,0,0">嗯 m24</d>
<d p="1977.9944939613342,1,25,16777215,0,0,0,0">66666666666666666</d>
<d p="1979.7024593353271,1,25,16777215,0,0,0,0">66666666666666666666666</d>
<d p="1979.7034599781036,1,25,16777215,0,0,0,0">66666666666666666666666666</d>
<d p="1981.2089531421661,1,25,16777215,0,0,0,0">666666666666</d>
<d p="1983.3187012672424,1,25,16777215,0,0,0,0">666666666666666</d>
<d p="1985.928528547287,1,25,16777215,0,0,0,0">66666666666666666</d>
<d p="1986.1294991970062,1,25,16777215,0,0,0,0">6666666666</d>
<d p="1986.4306724071503,1,25,16777215,0,0,0,0">三存活你们占俩</d>
<d p="1987.034573316574,1,25,16777215,0,0,0,0">lice</d>
<d p="1989.3424923419952,1,25,16777215,0,0,0,0">66666666666666</d>
<d p="1989.4433267116547,1,25,16777215,0,0,0,0">666666666666666666666666</d>
<d p="1991.7504255771637,1,25,16777215,0,0,0,0">电音</d>
<d p="1991.8520407676697,1,25,16777215,0,0,0,0">烟雾很重要</d>
<d p="1991.8525409698486,1,25,16777215,0,0,0,0">根本听不清</d>
<d p="1993.05637383461,1,25,16777215,0,0,0,0">66666666666</d>
<d p="1994.5618696212769,1,25,16777215,0,0,0,0">网络</d>
<d p="1994.6624689102173,1,25,16777215,0,0,0,0">66666666666666</d>
<d p="1995.0658550262451,1,25,16777215,0,0,0,0">66666666666666</d>
<d p="1997.3718266487122,1,25,16777215,0,0,0,0">厉害厉害。。。。。</d>
<d p="1998.3752944469452,1,25,16777215,0,0,0,0">6666666</d>
<d p="1998.4762625694275,1,25,16777215,0,0,0,0">全体起立</d>
<d p="1998.5783431529999,1,25,16777215,0,0,0,0">终于赢了</d>
<d p="1998.6806070804596,1,25,16777215,0,0,0,0">6666666666666666</d>
<d p="1998.9833889007568,1,25,16777215,0,0,0,0">好像却是维护了</d>
<d p="2000.7889523506165,1,25,16777215,0,0,0,0">恭喜，你游戏玩不了了</d>
<d p="2001.290890455246,1,25,16777215,0,0,0,0">6666666666666666666666</d>
<d p="2001.3914022445679,1,25,16777215,0,0,0,0">又吃鸡了</d>
<d p="2001.592809677124,1,25,16777215,0,0,0,0">可以可以</d>
<d p="2002.8987514972687,1,25,16777215,0,0,0,0">服务器维护了？</d>
<d p="2003.5020470619202,1,25,16777215,0,0,0,0">66666666666</d>
<d p="2004.0051429271698,1,25,16777215,0,0,0,0">电音小哥可以的啊</d>
<d p="2005.9113564491272,1,25,16777215,0,0,0,0">告诉美国小哥的麦有问题 让他处理</d>
<d p="2006.5160717964172,1,25,16777215,0,0,0,0">小哥笑到颤抖</d>
<d p="2006.9175369739532,1,25,16777215,0,0,0,0">全体起立</d>
<d p="2009.7252831459045,1,25,16777215,0,0,0,0">服务器维护</d>
<d p="2009.827076435089,1,25,16777215,0,0,0,0">666666</d>
<d p="2011.8357028961182,1,25,16777215,0,0,0,0">我觉得亚服都是LYB 太难打了</d>
<d p="2012.83922290802,1,25,16777215,0,0,0,0">666666666666666666666</d>
<d p="2014.5479669570923,1,25,16777215,0,0,0,0">叫他把手机拿远点叫他把手机拿远点叫他把手机拿远点</d>
<d p="2016.6528735160828,1,25,16777215,0,0,0,0">666</d>
<d p="2017.3551306724548,1,25,16777215,0,0,0,0">自带电音</d>
<d p="2019.0600872039795,1,25,16777215,0,0,0,0">我去美服就好打的多了</d>
<d p="2019.7653367519379,1,25,16777215,0,0,0,0">666</d>
<d p="2021.0703654289246,1,25,16777215,0,0,0,0">这歌叫什么名字</d>
<d p="2030.8030309677124,1,25,16777215,0,0,0,0">和他说他笑起来就想凯恩韦斯特</d>
<d p="2031.3033652305603,1,25,16777215,0,0,0,0">666666666</d>
<d p="2038.5319352149963,1,25,16777215,0,0,0,0">你告诉小哥 他的麦有问题</d>
<d p="2041.1447126865387,1,25,16777215,0,0,0,0">主播nb办波卡</d>
<d p="2046.2669205665588,1,25,16777215,0,0,0,0">BGM</d>
<d p="2046.4675555229187,1,25,16777215,0,0,0,0">求bgm</d>
<d p="2047.3723618984222,1,25,16777215,0,0,0,0">亚服外挂多</d>
<d p="2049.983965396881,1,25,16777215,0,0,0,0">应该是网络问题</d>
<d p="2056.1020772457123,1,25,16777215,0,0,0,0">网不好，就这样</d>
<d p="2057.6077387332916,1,25,16777215,0,0,0,0">快下了吧</d>
<d p="2066.5379915237427,1,25,16777215,0,0,0,0">刚才的BGM</d>
<d p="2067.0726985931396,1,25,16777215,0,0,0,0">雾山英文这么好的</d>
<d p="2070.3875935077667,1,25,16777215,0,0,0,0">是什么 </d>
<d p="2073.4995353221893,1,25,16777215,0,0,0,0">点点点</d>
<d p="2076.3127806186676,1,25,16777215,0,0,0,0">这不是专门的电音效果吗？</d>
<d p="2078.729456424713,1,25,16777215,0,0,0,0">刚才的BGM是什么。</d>
<d p="2083.048812389374,1,25,16777215,0,0,0,0">天天吃鸡，要发胖了</d>
<d p="2083.450464487076,1,25,16777215,0,0,0,0">看样子</d>
<d p="2087.477065563202,1,25,16777215,0,0,0,0">点了一下关注，变成橙色了</d>
<d p="2088.588456630707,1,25,16777215,0,0,0,0">53我要给你生猴子</d>
<d p="2089.295756340027,1,25,16777215,0,0,0,0">美服挺好打</d>
<d p="2091.0174198150635,1,25,16777215,0,0,0,0">Background music is what</d>
<d p="2096.949462413788,1,25,16777215,0,0,0,0">大声说，办什么</d>
<d p="2101.9660885334015,1,25,16777215,0,0,0,0">ggle</d>
<d p="2102.368066549301,1,25,16777215,0,0,0,0">我这游戏好玩啊 没维护啊</d>
<d p="2106.3823671340942,1,25,16777215,0,0,0,0">刚才的bgm是什么</d>
<d p="2108.387338399887,1,25,16777215,0,0,0,0">从你玩守望先锋就一直关注着你 加油</d>
<d p="2108.6892199516296,1,25,16777215,0,0,0,0">510</d>
<d p="2109.292694091797,1,25,16777215,0,0,0,0">GG你也上不去了</d>
<d p="2111.5998084545135,1,25,16777215,0,0,0,0">510.</d>
<d p="2113.4054629802704,1,25,16777215,0,0,0,0">鸭姐</d>
<d p="2114.4079537391663,1,25,16777215,0,0,0,0">我实在是办不动了</d>
<d p="2116.715965270996,1,25,16777215,0,0,0,0">服务器炸</d>
<d p="2119.6271238327026,1,25,16777215,0,0,0,0">我的钱都给灾区了</d>
<d p="2122.335142850876,1,25,16777215,0,0,0,0">刚才的BGM是什么。刚才的BGM是什么。</d>
<d p="2122.5380232334137,1,25,16777215,0,0,0,0">510..</d>
<d p="2122.7392132282257,1,25,16777215,0,0,0,0">bgm</d>
<d p="2129.4643700122833,1,25,16777215,0,0,0,0">bgmbgm</d>
<d p="2132.1697084903717,1,25,16777215,0,0,0,0">能进</d>
<d p="2138.490023612976,1,25,16777215,0,0,0,0">我，打钱</d>
<d p="2141.3996176719666,1,25,16777215,0,0,0,0">[emot:dy003]</d>
<d p="2148.9208312034607,1,25,16777215,0,0,0,0">BMGBGM</d>
<d p="2149.020897626877,1,25,16777215,0,0,0,0">very sexly</d>
<d p="2153.7345340251923,1,25,16777215,0,0,0,0">.</d>
<d p="2153.9365055561066,1,25,16777215,0,0,0,0">刚才的BGM是什么。</d>
<d p="2154.0387041568756,1,25,16777215,0,0,0,0">刚才的bgm</d>
<d p="2154.2394983768463,1,25,16777215,0,0,0,0">。</d>
<d p="2165.776476621628,1,25,16777215,0,0,0,0">刚才BGM是loving strangers</d>
<d p="2173.8010976314545,1,25,16777215,0,0,0,0">可以不穿衣服吗</d>
<d p="2174.2040045261383,1,25,16777215,0,0,0,0">对</d>
<d p="2177.213709592819,1,25,16777215,0,0,0,0">Hop</d>
<d p="2178.217758178711,1,25,16777215,0,0,0,0">也不知道9527怎么样了</d>
<d p="2182.0308883190155,1,25,16777215,0,0,0,0">水舞小姐姐也穿这个</d>
<d p="2189.1499865055084,1,25,16777215,0,0,0,0">hop的，知道战国hop么</d>
<d p="2190.153586626053,1,25,16777215,0,0,0,0">thank you</d>
<d p="2192.665061235428,1,25,16777215,0,0,0,0">怎么进去时</d>
<d p="2192.866901397705,1,25,16777215,0,0,0,0">不懂</d>
<d p="2202.59876871109,1,25,16777215,0,0,0,0">[emot:dy002]</d>
<d p="2205.913219690323,1,25,16777215,0,0,0,0">2333333333333</d>
<d p="2218.9479517936707,1,25,16777215,0,0,0,0">i dont like  this mc anymore</d>
<d p="2225.7683868408203,1,25,16777215,0,0,0,0">游戏可以进了吗？我刚进不去</d>
<d p="2227.17361164093,1,25,16777215,0,0,0,0">主播再见 去网吧吃鸡了</d>
<d p="2230.483657360077,1,25,16777215,0,0,0,0">好卡啊</d>
<d p="2232.491549730301,1,25,16777215,0,0,0,0">53和水舞双排效果肯定暴炸</d>
<d p="2232.7926683425903,1,25,16777215,0,0,0,0">9527也不知道还好不好</d>
<d p="2241.1252870559692,1,25,16777215,0,0,0,0">为什么你还能玩</d>
<d p="2247.6443338394165,1,25,16777215,0,0,0,0">关服了</d>
<d p="2252.560046195984,1,25,16777215,0,0,0,0">我显示的服务器关闭= =</d>
<d p="2258.1749835014343,1,25,16777215,0,0,0,0">水舞小姐姐很刚</d>
<d p="2271.1245136260986,1,25,16777215,0,0,0,0">主播有优先权可以玩</d>
<d p="2276.042896747589,1,25,16777215,0,0,0,0">我的也进不去了</d>
<d p="2277.7489914894104,1,25,16777215,0,0,0,0">水上漂小姐姐</d>
<d p="2279.054034471512,1,25,16777215,0,0,0,0">只看到53今天带那个小哥明天带那个小哥</d>
<d p="2285.776746749878,1,25,16777215,0,0,0,0">这哥们还不睡觉</d>
<d p="2299.6183943748474,1,25,16777215,0,0,0,0">别的主播都是这一个小姐姐那一个小姐姐</d>
<d p="2309.847104549408,1,25,16777215,0,0,0,0">卡卡的</d>
<d p="2312.458161830902,1,25,16777215,0,0,0,0">服务器关了吗</d>
<d p="2312.558969259262,1,25,16777215,0,0,0,0">还好你没去学校 落地成沙</d>
<d p="2316.2685317993164,1,25,16777215,0,0,0,0">Water dancing</d>
<d p="2323.402632713318,1,25,16777215,0,0,0,0">亚服可能关了</d>
<d p="2323.5034396648407,1,25,16777215,0,0,0,0">你们别说了，再说就暴露了</d>
<d p="2336.458901643753,1,25,16777215,0,0,0,0">可以进了</d>
<d p="2337.8636903762817,1,25,16777215,0,0,0,0">这是美服</d>
<d p="2345.9896471500397,1,25,16777215,0,0,0,0">谁开到小裙子了？</d>
<d p="2349.10307097435,1,25,16777215,0,0,0,0">那我还是在家不出去了</d>
<d p="2355.5221149921417,1,25,16777215,0,0,0,0">他的是美服我换一下试试</d>
<d p="2360.8460009098053,1,25,16777215,0,0,0,0">别膨胀，</d>
<d p="2364.9605810642242,1,25,16777215,0,0,0,0">联邦快递</d>
<d p="2378.1930339336395,1,25,16777215,0,0,0,0">好了亚服能上了</d>
<d p="2378.3947327136993,1,25,16777215,0,0,0,0">中美快递</d>
<d p="2393.2394638061523,1,25,16777215,0,0,0,0">国际快递，中美合营</d>
<d p="2400.3624358177185,1,25,16777215,0,0,0,0">应该是中美联合快递</d>
<d p="2416.7130467891693,1,25,16777215,0,0,0,0">缺药</d>
<d p="2417.5156302452087,1,25,16777215,0,0,0,0">镜子呢</d>
<d p="2423.9350078105927,1,25,16777215,0,0,0,0">膨胀</d>
<d p="2426.5431945323944,1,25,16777215,0,0,0,0">那你还缺个镜子</d>
<d p="2430.657215356827,1,25,16777215,0,0,0,0">人呢</d>
<d p="2434.0677831172943,1,25,16777215,0,0,0,0">我落地2把狙  没活过1分钟</d>
<d p="2441.892107963562,1,25,16777215,0,0,0,0">3栋房子能养4个人了。</d>
<d p="2442.4938793182373,1,25,16777215,0,0,0,0">锅也没有</d>
<d p="2463.857941865921,1,25,16777215,0,0,0,0">小姐姐呢</d>
<d p="2490.6653101444244,1,25,16777215,0,0,0,0">落地98k然后直接跑。跑到大厂房来了个八倍。然后一枪没zhon</d>
<d p="2507.619306087494,1,25,16777215,0,0,0,0">53带雪哥吃鸡 吧</d>
<d p="2508.6243228912354,1,25,16777215,0,0,0,0">斗鱼英语最溜得吃鸡主播？</d>
<d p="2514.139850616455,1,25,16777215,0,0,0,0">我去帮帮他（搜刮一下）</d>
<d p="2516.8478400707245,1,25,16777215,0,0,0,0">不带</d>
<d p="2529.0939881801605,1,25,16777215,0,0,0,0">这么肥</d>
<d p="2537.2228701114655,1,25,16777215,0,0,0,0">雪哥号称吃鸡女王还用带吗</d>
<d p="2551.570675134659,1,25,16777215,0,0,0,0">带个不男不女的干嘛</d>
<d p="2557.291284799576,1,25,16777215,0,0,0,0">主播什么配置的电脑啊</d>
<d p="2559.0987045764923,1,25,16777215,0,0,0,0">先哩个flag</d>
<d p="2574.346535205841,1,25,16777215,0,0,0,0">大衣。。。膨胀了</d>
<d p="2583.575065135956,1,25,16777215,0,0,0,0">这么膨胀的吗</d>
<d p="2586.380526781082,1,25,16777215,0,0,0,0">鼠文强再战江湖</d>
<d p="2587.3846533298492,1,25,16777215,0,0,0,0">决胜大衣</d>
<d p="2587.3856539726257,1,25,16777215,0,0,0,0">问问他们那几点了，这个夜猫子</d>
<d p="2603.130662202835,1,25,16777215,0,0,0,0">这也是肥?</d>
<d p="2603.43212223053,1,25,16777215,0,0,0,0">刚刚bgm拼一下</d>
<d p="2610.256191968918,1,25,16777215,0,0,0,0">大衣太难看了</d>
<d p="2617.093546628952,1,25,16777215,0,0,0,0">天命大衣</d>
<d p="2630.2340347766876,1,25,16777215,0,0,0,0">穷得一匹</d>
<d p="2639.9677629470825,1,25,16777215,0,0,0,0">M16装消音声音还是很大</d>
<d p="2650.603790998459,1,25,16777215,0,0,0,0">小哥缺啥啊</d>
<d p="2664.777005672455,1,25,16777215,0,0,0,0">缺爱吧。。</d>
<d p="2673.818810939789,1,25,16777215,0,0,0,0">三级头都没有98k都没有，真穷，膨胀什么呀</d>
<d p="2676.227613210678,1,25,16777215,0,0,0,0">头真的不重要 上把两个绿帽子吃鸡</d>
<d p="2681.7597663402557,1,25,16777215,0,0,0,0">稳住我们能送</d>
<d p="2738.86407661438,1,25,16777215,0,0,0,0">雪妹妹唱歌贼好听</d>
<d p="2755.2094378471375,1,25,16777215,0,0,0,0">雾山为啥英语这么好</d>
<d p="2759.1200909614563,1,25,16777215,0,0,0,0">说雪妹妹唱歌好听的站住</d>
<d p="2765.14342546463,1,25,16777215,0,0,0,0">这么富，一腔没开</d>
<d p="2766.447257757187,1,25,16777215,0,0,0,0">[emot:dy115]</d>
<d p="2771.057046890259,1,25,16777215,0,0,0,0">天降正义</d>
<d p="2771.558870792389,1,25,16777215,0,0,0,0">53好莱坞毕业的</d>
<d p="2778.0787222385406,1,25,16777215,0,0,0,0">要被劈死了</d>
<d p="2779.1854164600372,1,25,16777215,0,0,0,0">要炸死</d>
<d p="2781.1933603286743,1,25,16777215,0,0,0,0">等一个天降正义</d>
<d p="2783.100067138672,1,25,16777215,0,0,0,0">天降正义</d>
<d p="2783.8034374713898,1,25,16777215,0,0,0,0">清脆的98k</d>
<d p="2785.20782995224,1,25,16777215,0,0,0,0">天降正义</d>
<d p="2787.9167370796204,1,25,16777215,0,0,0,0">天降正义</d>
<d p="2788.517639398575,1,25,16777215,0,0,0,0">好莱坞推车学院？</d>
<d p="2789.826312303543,1,25,16777215,0,0,0,0">天降正义</d>
<d p="2795.5411319732666,1,25,16777215,0,0,0,0">天降正义</d>
<d p="2827.740278482437,1,25,16777215,0,0,0,0">1111</d>
<d p="2837.572045326233,1,25,16777215,0,0,0,0">一发炮弹</d>
<d p="2838.073392868042,1,25,16777215,0,0,0,0">法鸡天降正义英语怎么说的？吊大的教我</d>
<d p="2840.4838230609894,1,25,16777215,0,0,0,0">779807周星驰林正英李连杰赌神鬼片点播</d>
<d p="2848.409603834152,1,25,16777215,0,0,0,0">sky down 正义</d>
<d p="2852.926838874817,1,25,16777215,0,0,0,0">rain from above</d>
<d p="2854.232456922531,1,25,16777215,0,0,0,0">233333</d>
<d p="2858.949176311493,1,25,16777215,0,0,0,0">53是哈佛毕业的，英语肯定好</d>
<d p="2861.0532896518707,1,25,16777215,0,0,0,0">6666</d>
<d p="2861.8559584617615,1,25,16777215,0,0,0,0">中美联合快递为您派送中</d>
<d p="2862.157510280609,1,25,16777215,0,0,0,0">justice</d>
<d p="2867.175463438034,1,25,16777215,0,0,0,0">jutics</d>
<d p="2869.7844688892365,1,25,16777215,0,0,0,0">justice rain from above</d>
<d p="2870.487137079239,1,25,16777215,0,0,0,0">justice rain from above</d>
<d p="2876.2025067806244,1,25,16777215,0,0,0,0">judement from sky</d>
<d p="2880.1135568618774,1,25,16777215,0,0,0,0">不是在维护吗</d>
<d p="2881.6200630664825,1,25,16777215,0,0,0,0">哈尔滨佛学院确实要求英文</d>
<d p="2882.6242549419403,1,25,16777215,0,0,0,0">阿贡佛罗多美死滴</d>
<d p="2884.630222558975,1,25,16777215,0,0,0,0">53快递，中美合资</d>
<d p="2886.2339000701904,1,25,16777215,0,0,0,0">justice </d>
<d p="2891.047224521637,1,25,16777215,0,0,0,0">或许有人跟着我们</d>
<d p="2900.403096675873,1,25,16777215,0,0,0,0">那叫behind。。。</d>
<d p="2903.213434457779,1,25,16777215,0,0,0,0">66666666666666</d>
<d p="2907.454610347748,1,25,16777215,0,0,0,0">玩这个游戏需要什么配置？</d>
<d p="2911.472920179367,1,25,16777215,0,0,0,0">夹击妹抖 from above</d>
<d p="2917.6377832889557,1,25,16777215,0,0,0,0">轰炸区有人</d>
<d p="2921.948452234268,1,25,16777215,0,0,0,0">吸纳要英语过四级</d>
<d p="2934.6863527297974,1,25,16777215,0,0,0,0">53你这样和美国小哥交流太少，没有节目效果啊</d>
<d p="2936.7907807826996,1,25,16777215,0,0,0,0">夹击美豆的等我</d>
<d p="2938.999207019806,1,25,16777215,0,0,0,0">自己配个主机需要多少钱</d>
<d p="2948.6342735290527,1,25,16777215,0,0,0,0">M16是用单发还是连发好</d>
<d p="2961.373192548752,1,25,16777215,0,0,0,0">和美国小哥聊聊美女 性啥的</d>
<d p="2962.075602054596,1,25,16777215,0,0,0,0">主机3500起步</d>
<d p="2977.7228648662567,1,25,16777215,0,0,0,0">近就连发  远就单发</d>
<d p="2983.5417325496674,1,25,16777215,0,0,0,0">聊聊生活</d>
<d p="2988.5592103004456,1,25,16777215,0,0,0,0">都是连发，全自动，哪个去单发，近身等你改早死了</d>
<d p="2990.869978904724,1,25,16777215,0,0,0,0"> 3500别闹。。</d>
<d p="2991.773063659668,1,25,16777215,0,0,0,0">给大屌递茶</d>
<d p="2993.384122133255,1,25,16777215,0,0,0,0">4500爽玩</d>
<d p="2995.086925268173,1,25,16777215,0,0,0,0">是的53 你应该多跟小哥聊 问问她知不知道水雾</d>
<d p="3009.1284580230713,1,25,16777215,0,0,0,0">53教小哥说两句中文</d>
<d p="3012.8397562503815,1,25,16777215,0,0,0,0">4500够用吗</d>
<d p="3014.9471247196198,1,25,16777215,0,0,0,0">天降正义</d>
<d p="3024.479350090027,1,25,16777215,0,0,0,0">最少都得四千八的电脑</d>
<d p="3029.9179558753967,1,25,16777215,0,0,0,0">53好6啊</d>
<d p="3032.5283341407776,1,25,16777215,0,0,0,0">八倍</d>
<d p="3033.1312987804413,1,25,16777215,0,0,0,0">快递车</d>
<d p="3034.033756494522,1,25,16777215,0,0,0,0">4500不含显示器够了吧</d>
<d p="3037.045315504074,1,25,16777215,0,0,0,0">头盔</d>
<d p="3037.246562719345,1,25,16777215,0,0,0,0">炸死</d>
<d p="3040.357752799988,1,25,16777215,0,0,0,0">i5四核就可以</d>
<d p="3040.559274673462,1,25,16777215,0,0,0,0">8倍</d>
<d p="3041.062237739563,1,25,16777215,0,0,0,0">等一个被炸死</d>
<d p="3049.583555698395,1,25,16777215,0,0,0,0">走啊</d>
<d p="3053.793352842331,1,25,16777215,0,0,0,0">弹夹</d>
<d p="3060.532467365265,1,25,16777215,0,0,0,0">4500能玩 60针吧，但是有烟雾就卡</d>
<d p="3063.4391775131226,1,25,16777215,0,0,0,0">换个头啊</d>
<d p="3068.1551444530487,1,25,16777215,0,0,0,0">天降大雨</d>
<d p="3068.656316280365,1,25,16777215,0,0,0,0">要被炸死</d>
<d p="3078.202422142029,1,25,16777215,0,0,0,0">把钱用在刀刃上</d>
<d p="3089.2447595596313,1,25,16777215,0,0,0,0">8瓶饮料 怕是要尿尿哦</d>
<d p="3094.579135656357,1,25,16777215,0,0,0,0">求主播的电脑配置，我想配一个</d>
<d p="3101.401465177536,1,25,16777215,0,0,0,0">所以还是买把才到切肉好了</d>
<d p="3138.717870235443,1,25,16777215,0,0,0,0">主播都是过万的电脑</d>
<d p="3144.537262439728,1,25,16777215,0,0,0,0">5000的电脑就是送快递的！最少7000吃鸡</d>
<d p="3152.761569738388,1,25,16777215,0,0,0,0">哈哈</d>
<d p="3155.280595302582,1,25,16777215,0,0,0,0">i3+GTX1060+16G可以了吧</d>
<d p="3156.4844036102295,1,25,16777215,0,0,0,0">8倍镜都不要吗</d>
<d p="3160.993194103241,1,25,16777215,0,0,0,0">i5 15g内存  1060 妥妥的</d>
<d p="3164.002133846283,1,25,16777215,0,0,0,0">7000笔记本都够了老铁</d>
<d p="3170.0226109027863,1,25,16777215,0,0,0,0">16g内存</d>
<d p="3181.7765300273895,1,25,16777215,0,0,0,0">好像这游戏不吃cpu</d>
<d p="3182.878128528595,1,25,16777215,0,0,0,0">15G内存 有么</d>
<d p="3184.282157421112,1,25,16777215,0,0,0,0">I5吧 i3 有点差</d>
<d p="3192.610426902771,1,25,16777215,0,0,0,0">我用我家手电筒都能吃鸡</d>
<d p="3193.4136114120483,1,25,16777215,0,0,0,0">网吧五千的电脑就行</d>
<d p="3197.9278984069824,1,25,16777215,0,0,0,0">r5不行么要什么i5</d>
<d p="3202.4412112236023,1,25,16777215,0,0,0,0">I5 16G 1050</d>
<d p="3204.0499641895294,1,25,16777215,0,0,0,0">这游戏I5就行。就是吃显卡</d>
<d p="3207.661111831665,1,25,16777215,0,0,0,0">稳稳的</d>
<d p="3216.0941739082336,1,25,16777215,0,0,0,0">这老外好gay</d>
<d p="3216.195056438446,1,25,16777215,0,0,0,0">游戏还需要加速器吗</d>
<d p="3220.3085293769836,1,25,16777215,0,0,0,0">I7-1060-16g</d>
<d p="3226.23046875,1,25,16777215,0,0,0,0">1050不行好像 1050Ti都算最低了</d>
<d p="3232.4491119384766,1,25,16777215,0,0,0,0">CHINA .</d>
<d p="3238.1669142246246,1,25,16777215,0,0,0,0">chinagh</d>
<d p="3244.685396671295,1,25,16777215,0,0,0,0">爆头弄死一个中国小伙子</d>
<d p="3254.0159089565277,1,25,16777215,0,0,0,0">你和老外杀死了同胞！！</d>
<d p="3263.383854866028,1,25,16777215,0,0,0,0">叛国了</d>
<d p="3269.9191138744354,1,25,16777215,0,0,0,0">现在不播守望了吗</d>
<d p="3274.8318507671356,1,25,16777215,0,0,0,0">CHINA NO.1 American NO.2，alway</d>
<d p="3276.634551525116,1,25,16777215,0,0,0,0">叛国啦 兄弟</d>
<d p="3281.24742603302,1,25,16777215,0,0,0,0">你杀了Chinagh</d>
<d p="3281.848819255829,1,25,16777215,0,0,0,0">游戏而已</d>
<d p="3282.853739261627,1,25,16777215,0,0,0,0">不就玩个游戏吗，怎么又叛国了</d>
<d p="3287.6677646636963,1,25,16777215,0,0,0,0">脑残吧</d>
<d p="3289.1719303131104,1,25,16777215,0,0,0,0">说叛国就过分了</d>
<d p="3292.1837315559387,1,25,16777215,0,0,0,0">你特么 = =</d>
<d p="3294.393272638321,1,25,16777215,0,0,0,0">节奏飞起</d>
<d p="3296.70205450058,1,25,16777215,0,0,0,0">叛你吗比？游戏就叛国了？</d>
<d p="3296.7025558948517,1,25,16777215,0,0,0,0">懂玩笑么？？？？？？？？？？？？？</d>
<d p="3299.014771938324,1,25,16777215,0,0,0,0">Chinglish</d>
<d p="3301.4265644550323,1,25,16777215,0,0,0,0">等着被杀吗</d>
<d p="3301.8284709453583,1,25,16777215,0,0,0,0">moto?</d>
<d p="3303.0316863059998,1,25,16777215,0,0,0,0">傻较真。。</d>
<d p="3304.7375774383545,1,25,16777215,0,0,0,0">你妈比单排还不是一样傻中国人</d>
<d p="3305.44198179245,1,25,16777215,0,0,0,0">真逗</d>
<d p="3305.842709302902,1,25,16777215,0,0,0,0">a 摩托</d>
<d p="3305.843209505081,1,25,16777215,0,0,0,0">你玩游戏天天被国人杀怎么说</d>
<d p="3310.855471134186,1,25,16777215,0,0,0,0">安静，爱国就上前线当兵，别在这里费劲</d>
<d p="3311.357198238373,1,25,16777215,0,0,0,0">国怎么叛  求教</d>
<d p="3317.4775292873383,1,25,16777215,0,0,0,0">我去，53去突击学了雅思？</d>
<d p="3317.97967672348,1,25,16777215,0,0,0,0">我天天玩亚服天天被国人杀。。难道都叛啦？-。-</d>
<d p="3318.8828444480896,1,25,16777215,0,0,0,0">说乳滑就过分了</d>
<d p="3319.987010240555,1,25,16777215,0,0,0,0">神tm叛国，其他人还不一样，不过是自己而已</d>
<d p="3320.2885677814484,1,25,16777215,0,0,0,0">牛批牛批</d>
<d p="3322.8976016044617,1,25,16777215,0,0,0,0">给人杀就是傻  杀人就是叛国</d>
<d p="3324.1015198230743,1,25,16777215,0,0,0,0">我想去美国 能给个绿卡么</d>
<d p="3326.711888551712,1,25,16777215,0,0,0,0">节奏狗全nm闭嘴</d>
<d p="3328.718498468399,1,25,16777215,0,0,0,0">人家吐槽下，你们怎么就当真了</d>
<d p="3329.723957300186,1,25,16777215,0,0,0,0">叫bike吧</d>
<d p="3330.0250906944275,1,25,16777215,0,0,0,0">怎么有人带节奏了？</d>
<d p="3335.067414045334,1,25,16777215,0,0,0,0">你打cf天天杀不是叛国？</d>
<d p="3335.5689249038696,1,25,16777215,0,0,0,0">明明是开玩笑的也有这么多人当真哈哈</d>
<d p="3337.877257347107,1,25,16777215,0,0,0,0">玩笑都开不起了。各位弹幕大神。</d>
<d p="3343.0953834056854,1,25,16777215,0,0,0,0">哈哈</d>
<d p="3343.3965849876404,1,25,16777215,0,0,0,0">这个熟悉的地方</d>
<d p="3344.2992582321167,1,25,16777215,0,0,0,0">麻烦把15级以下的都禁言好吗</d>
<d p="3346.301995038986,1,25,16777215,0,0,0,0">被国人杀是刑事案件</d>
<d p="3351.114819049835,1,25,16777215,0,0,0,0">白鹅都不浮绿水 就服你。</d>
<d p="3352.7238256931305,1,25,16777215,0,0,0,0">天命圈</d>
<d p="3359.3487281799316,1,25,16777215,0,0,0,0">换个愉快的话题</d>
<d p="3363.16552901268,1,25,16777215,0,0,0,0">关弹幕保智商</d>
<d p="3367.677762746811,1,25,16777215,0,0,0,0">劳资要关弹幕保智商了</d>
<d p="3375.399979829788,1,25,16777215,0,0,0,0">雾山这把能不能吃鸡</d>
<d p="3379.6161148548126,1,25,16777215,0,0,0,0">较真的不适合玩弹幕</d>
<d p="3380.322026491165,1,25,16777215,0,0,0,0">这游戏8g内存能玩吗</d>
<d p="3381.9293587207794,1,25,16777215,0,0,0,0">喂110这里有人要杀我</d>
<d p="3382.0303366184235,1,25,16777215,0,0,0,0">我赌100鱼丸</d>
<d p="3387.245412349701,1,25,16777215,0,0,0,0">23333333333333333</d>
<d p="3387.848124027252,1,25,16777215,0,0,0,0">吃鸡日韩红</d>
<d p="3389.287924051285,1,25,16777215,0,0,0,0">666</d>
<d p="3390.0909535884857,1,25,16777215,0,0,0,0">66666666666</d>
<d p="3392.0020685195923,1,25,16777215,0,0,0,0">23333333333</d>
<d p="3392.102635860443,1,25,16777215,0,0,0,0">66666666666666</d>
<d p="3392.204703807831,1,25,16777215,0,0,0,0">666666666</d>
<d p="3392.705584526062,1,25,16777215,0,0,0,0">哈哈哈哈哈</d>
<d p="3392.706084728241,1,25,16777215,0,0,0,0">66666666666666666666</d>
<d p="3392.806651830673,1,25,16777215,0,0,0,0">66666</d>
<d p="3393.308422088623,1,25,16777215,0,0,0,0">摔死</d>
<d p="3393.7105824947357,1,25,16777215,0,0,0,0">哈哈哈哈哈哈哈</d>
<d p="3394.212597131729,1,25,16777215,0,0,0,0">哈哈哈哈哈哈啊哈</d>
<d p="3394.6146845817566,1,25,16777215,0,0,0,0">听说你很会开车</d>
<d p="3394.7158908843994,1,25,16777215,0,0,0,0">哈哈哈</d>
<d p="3394.8164014816284,1,25,16777215,0,0,0,0">色情主播,我报警啦！</d>
<d p="3394.816901922226,1,25,16777215,0,0,0,0">233333</d>
<d p="3395.420019388199,1,25,16777215,0,0,0,0">666666666666666666666666</d>
<d p="3395.7213118076324,1,25,16777215,0,0,0,0">啊哈哈</d>
<d p="3395.9227316379547,1,25,16777215,0,0,0,0">66666666666</d>
<d p="3396.224140882492,1,25,16777215,0,0,0,0">6666666666666</d>
<d p="3396.324679374695,1,25,16777215,0,0,0,0">666666666666666</d>
<d p="3396.3261761665344,1,25,16777215,0,0,0,0">牛逼</d>
<d p="3396.4268300533295,1,25,16777215,0,0,0,0">6666666</d>
<d p="3396.8292248249054,1,25,16777215,0,0,0,0">66666666666666666666666666</d>
<d p="3397.0313923358917,1,25,16777215,0,0,0,0">你这。。。。。</d>
<d p="3397.1320753097534,1,25,16777215,0,0,0,0">日常翻车</d>
<d p="3397.432877779007,1,25,16777215,0,0,0,0">66666666666666</d>
<d p="3399.0389580726624,1,25,16777215,0,0,0,0">66666666666</d>
<d p="3399.1399898529053,1,25,16777215,0,0,0,0">66666666666666666</d>
<d p="3399.2418842315674,1,25,16777215,0,0,0,0">哈哈哈哈哈哈哈哈哈哈哈哈哈哈</d>
<d p="3399.2433848381042,1,25,16777215,0,0,0,0">哈哈哈哈翻车了</d>
<d p="3399.2438848018646,1,25,16777215,0,0,0,0">6666666666</d>
<d p="3399.244884252548,1,25,16777215,0,0,0,0">翻车</d>
<d p="3399.2453846931458,1,25,16777215,0,0,0,0">66666666666</d>
<d p="3399.3469004631042,1,25,16777215,0,0,0,0">[emot:dy101]</d>
<d p="3399.547557592392,1,25,16777215,0,0,0,0">平地翻车</d>
<d p="3399.7497062683105,1,25,16777215,0,0,0,0">6666666666666</d>
<d p="3399.9504816532135,1,25,16777215,0,0,0,0">6666</d>
<d p="3400.051069021225,1,25,16777215,0,0,0,0">666666666666666666666</d>
<d p="3400.255208492279,1,25,16777215,0,0,0,0">66666</d>
<d p="3400.5570299625397,1,25,16777215,0,0,0,0">66666666666</d>
<d p="3402.364192724228,1,25,16777215,0,0,0,0">23333333333333333333333333</d>
<d p="3402.5671861171722,1,25,16777215,0,0,0,0">快递都没送到</d>
<d p="3402.5681867599487,1,25,16777215,0,0,0,0">太厉害，哈哈哈哈哈哈哈</d>
<d p="3403.977046728134,1,25,16777215,0,0,0,0">笑死人</d>
<d p="3404.177973985672,1,25,16777215,0,0,0,0">666666</d>
<d p="3404.679651260376,1,25,16777215,0,0,0,0">翻车</d>
<d p="3405.3816950321198,1,25,16777215,0,0,0,0">6666666666666666666666</d>
<d p="3405.78355550766,1,25,16777215,0,0,0,0">2333333333333</d>
<d p="3405.884341239929,1,25,16777215,0,0,0,0">哈哈哈哈哈哈哈哈哈哈哈哈哈哈哈哈哈哈哈哈哈哈哈哈哈哈哈哈哈哈</d>
<d p="3406.3865773677826,1,25,16777215,0,0,0,0">帅死</d>
<d p="3407.6906402111053,1,25,16777215,0,0,0,0">666666</d>
<d p="3408.793124437332,1,25,16777215,0,0,0,0">6666</d>
<d p="3409.2994656562805,1,25,16777215,0,0,0,0">666</d>
<d p="3410.0033979415894,1,25,16777215,0,0,0,0">666</d>
<d p="3410.3054580688477,1,25,16777215,0,0,0,0">快递</d>
<d p="3411.4091153144836,1,25,16777215,0,0,0,0">哈哈哈哈哈哈哈哈啊哈</d>
